html5rdf/__init__.py
html5rdf/_ihatexml.py
html5rdf/_inputstream.py
html5rdf/_tokenizer.py
html5rdf/_utils.py
html5rdf/constants.py
html5rdf/html5parser.py
html5rdf/serializer.py
html5rdf/_trie/__init__.py
html5rdf/_trie/_base.py
html5rdf/_trie/py.py
html5rdf/contrib/__init__.py
html5rdf/contrib/webencodings/__init__.py
html5rdf/contrib/webencodings/labels.py
html5rdf/contrib/webencodings/mklabels.py
html5rdf/contrib/webencodings/tests.py
html5rdf/contrib/webencodings/x_user_defined.py
html5rdf/filters/__init__.py
html5rdf/filters/alphabeticalattributes.py
html5rdf/filters/base.py
html5rdf/filters/inject_meta_charset.py
html5rdf/filters/lint.py
html5rdf/filters/optionaltags.py
html5rdf/filters/whitespace.py
html5rdf/treeadapters/__init__.py
html5rdf/treeadapters/genshi.py
html5rdf/treeadapters/sax.py
html5rdf/treebuilders/__init__.py
html5rdf/treebuilders/base.py
html5rdf/treebuilders/dom.py
html5rdf/treebuilders/etree.py
html5rdf/treebuilders/etree_lxml.py
html5rdf/treewalkers/__init__.py
html5rdf/treewalkers/base.py
html5rdf/treewalkers/dom.py
html5rdf/treewalkers/etree.py
html5rdf/treewalkers/etree_lxml.py
html5rdf/treewalkers/genshi.py
html5rdf-1.2.dist-info/AUTHORS.rst
html5rdf-1.2.dist-info/LICENSE
html5rdf-1.2.dist-info/METADATA
html5rdf-1.2.dist-info/WHEEL
html5rdf-1.2.dist-info/top_level.txt
html5rdf-1.2.dist-info/RECORD
