Metadata-Version: 2.1
Name: html5rdf
Version: 1.2
Summary: HTML parser based on the WHATWG HTML specification
Home-page: https://github.com/RDFLib/html5rdf
Author-email: Ashley Sommer <ashleysommer@gmail.com>, James Graham <james@hoppipolla.co.uk>
Maintainer: Ashley Sommer
Maintainer-email: ashleysommer@gmail.com
License: Copyright (c) 2006-2013 James Graham and other contributors
Classifier: Development Status :: 5 - Production/Stable
Classifier: Intended Audience :: Developers
Classifier: License :: OSI Approved :: MIT License
Classifier: Operating System :: OS Independent
Classifier: Programming Language :: Python
Classifier: Programming Language :: Python :: 3
Classifier: Programming Language :: Python :: 3.8
Classifier: Programming Language :: Python :: 3.9
Classifier: Programming Language :: Python :: 3.10
Classifier: Programming Language :: Python :: 3.11
Classifier: Programming Language :: Python :: 3.12
Classifier: Programming Language :: Python :: Implementation :: CPython
Classifier: Programming Language :: Python :: Implementation :: PyPy
Classifier: Topic :: Software Development :: Libraries :: Python Modules
Classifier: Topic :: Text Processing :: Markup :: HTML
Requires-Python: >=3.8
License-File: LICENSE
License-File: AUTHORS.rst
Provides-Extra: all
Requires-Dist: genshi>=0.7.1; extra == "all"
Requires-Dist: chardet>=2.2.1; extra == "all"
Requires-Dist: lxml>=3.4.0; platform_python_implementation == "CPython" and extra == "all"
Provides-Extra: chardet
Requires-Dist: chardet>=2.2.1; extra == "chardet"
Provides-Extra: genshi
Requires-Dist: genshi>=0.7.1; extra == "genshi"
Provides-Extra: lxml
Requires-Dist: lxml>=3.4.0; platform_python_implementation == "CPython" and extra == "lxml"
